ccdc_forest_detector/__init__.py
ccdc_forest_detector/detector.py
ccdc_forest_detector/utils.py
ccdc_forest_detector/visualization.py
ccdc_forest_change_detector-1.0.0.dist-info/LICENSE.txt
ccdc_forest_change_detector-1.0.0.dist-info/METADATA
ccdc_forest_change_detector-1.0.0.dist-info/WHEEL
ccdc_forest_change_detector-1.0.0.dist-info/top_level.txt
ccdc_forest_change_detector-1.0.0.dist-info/RECORD
