Metadata-Version: 2.1
Name: ccdc-forest-change-detector
Version: 1.0.0
Summary: Una librería para detección de cambios forestales usando CCDC con Google Earth Engine
Author-email: Tu Nombre <tu.email@example.com>
License: MIT
Project-URL: Homepage, https://github.com/tuusuario/ccdc-forest-change-detector
Project-URL: Bug Reports, https://github.com/tuusuario/ccdc-forest-change-detector/issues
Project-URL: Source, https://github.com/tuusuario/ccdc-forest-change-detector
Keywords: earth engine,remote sensing,forest monitoring,CCDC,change detection
Classifier: Development Status :: 4 - Beta
Classifier: Intended Audience :: Science/Research
Classifier: License :: OSI Approved :: MIT License
Classifier: Operating System :: OS Independent
Classifier: Programming Language :: Python :: 3
Classifier: Programming Language :: Python :: 3.8
Classifier: Programming Language :: Python :: 3.9
Classifier: Programming Language :: Python :: 3.10
Classifier: Programming Language :: Python :: 3.11
Classifier: Topic :: Scientific/Engineering :: GIS
Requires-Python: >=3.8
License-File: LICENSE.txt
Requires-Dist: earthengine-api >=0.1.380
Requires-Dist: geemap >=0.24.0
Requires-Dist: ipywidgets >=8.0.0
Requires-Dist: pandas >=1.5.0
